{"cameraMode":{"drawMode":0,"name":"Shaded","section":"Shading Mode"},"sceneLighting":true,"audioPlay":false,"sceneViewState":{"m_AlwaysRefresh":false,"showFog":true,"showSkybox":true,"showFlares":true,"showImageEffects":true,"showParticleSystems":true,"showVisualEffectGraphs":true,"m_FxEnabled":true},"in2DMode":false,"pivot":{"x":1.4905939102172852,"y":6.496596813201904,"z":14.259992599487305},"rotation":{"x":0.1135019063949585,"y":-0.7163869738578796,"z":0.11995261162519455,"w":0.6778881549835205},"size":7.30997896194458,"orthographic":false}